{"id":"id128.dcZJKZ_kVsQvbuGR.PECT6Bbv3kPe7fP7rSM6YIsFLT0DBVd7ZAdkANghHVkm9onsvAoSAw","title":"Blue Lock Season 2","title_japanese":"ブルーロック VS. U-20 JAPAN","title_synonyms":"Blue Lock 2nd Season","anime_type":"TV","manga_type":null,"manga_year":null,"anime_year":2024,"author":null,"studios":"8bit","episodes":14,"manga_tags":null,"age_rating":"PG-13 - TEENS 13 OR OLDER","airing_status":"COMPLETED","image_url":"https://cdn.myanimelist.net/images/anime/1584/144860l.webp","banner_1":null,"manga_status":null,"rating":7.5}